blurit.py
blurit-0.0.13.dist-info/LICENSE
blurit-0.0.13.dist-info/METADATA
blurit-0.0.13.dist-info/WHEEL
blurit-0.0.13.dist-info/top_level.txt
blurit-0.0.13.dist-info/RECORD
