Metadata-Version: 2.1
Name: blurit
Version: 0.0.13
Summary: This package is aimed to build to blur different portions of a image. Currently it blurs eyes in human photograph.
Home-page: https://github.com/iampabba/blur-it
Author: Anubharth Pabba
Author-email: bharath.pabba1@gmail.com
Classifier: Development Status :: 5 - Production/Stable
Classifier: License :: OSI Approved :: MIT License
Classifier: Programming Language :: Python :: 3
Classifier: Programming Language :: Python :: 3.6
Classifier: Programming Language :: Python :: 3.7
Classifier: Operating System :: OS Independent
License-File: LICENSE
Requires-Dist: opencv-python (~=4.1.2)
Requires-Dist: numpy (~=1.21)
Requires-Dist: dlib (~=19.19.0)
Provides-Extra: dev
Requires-Dist: pytest (>=3.7) ; extra == 'dev'
